prime_uve/__init__.py
prime_uve/cli/__init__.py
prime_uve/cli/activate.py
prime_uve/cli/configure.py
prime_uve/cli/decorators.py
prime_uve/cli/dir.py
prime_uve/cli/init.py
prime_uve/cli/list.py
prime_uve/cli/main.py
prime_uve/cli/output.py
prime_uve/cli/prune.py
prime_uve/cli/register.py
prime_uve/cli/shell.py
prime_uve/core/__init__.py
prime_uve/core/cache.py
prime_uve/core/env_file.py
prime_uve/core/paths.py
prime_uve/core/project.py
prime_uve/utils/__init__.py
prime_uve/utils/disk.py
prime_uve/utils/shell.py
prime_uve/utils/venv.py
prime_uve/utils/vscode.py
prime_uve/uve/__init__.py
prime_uve/uve/__main__.py
prime_uve/uve/wrapper.py
prime_uve-0.2.0.dist-info/WHEEL
prime_uve-0.2.0.dist-info/entry_points.txt
prime_uve-0.2.0.dist-info/METADATA
prime_uve-0.2.0.dist-info/RECORD
