Metadata-Version: 2.3
Name: prime-uve
Version: 0.2.0
Summary: A thin wrapper for uv with external venv management
Keywords: uv,venv,environment,python,package-manager,wrapper
Author: kompre
Author-email: kompre <s.follador@gmail.com>
License: MIT
Classifier: Intended Audience :: Developers
Classifier: License :: OSI Approved :: MIT License
Classifier: Programming Language :: Python :: 3
Classifier: Programming Language :: Python :: 3.13
Classifier: Topic :: Software Development :: Build Tools
Classifier: Topic :: System :: Installation/Setup
Classifier: Operating System :: OS Independent
Requires-Dist: filelock>=3.20.0
Requires-Dist: click>=8.0.0
Maintainer: kompre
Maintainer-email: kompre <s.follador@gmail.com>
Requires-Python: >=3.13
Project-URL: Changelog, https://github.com/kompre/prime-uve/releases
Project-URL: Homepage, https://github.com/kompre/prime-uve
Project-URL: Issues, https://github.com/kompre/prime-uve/issues
Project-URL: Repository, https://github.com/kompre/prime-uve
